odoo9_addon_sequence_check_digit-9.0.1.0.0.99.dev4-py2.7-nspkg.pth
odoo9_addon_sequence_check_digit-9.0.1.0.0.99.dev4.dist-info/METADATA
odoo9_addon_sequence_check_digit-9.0.1.0.0.99.dev4.dist-info/RECORD
odoo9_addon_sequence_check_digit-9.0.1.0.0.99.dev4.dist-info/WHEEL
odoo9_addon_sequence_check_digit-9.0.1.0.0.99.dev4.dist-info/namespace_packages.txt
odoo9_addon_sequence_check_digit-9.0.1.0.0.99.dev4.dist-info/top_level.txt
odoo_addons/sequence_check_digit/README.rst
odoo_addons/sequence_check_digit/__init__.py
odoo_addons/sequence_check_digit/__openerp__.py
odoo_addons/sequence_check_digit/i18n/ca.po
odoo_addons/sequence_check_digit/i18n/de.po
odoo_addons/sequence_check_digit/i18n/es.po
odoo_addons/sequence_check_digit/i18n/es_ES.po
odoo_addons/sequence_check_digit/i18n/fr.po
odoo_addons/sequence_check_digit/i18n/gl.po
odoo_addons/sequence_check_digit/i18n/it.po
odoo_addons/sequence_check_digit/i18n/nl_NL.po
odoo_addons/sequence_check_digit/i18n/pt_BR.po
odoo_addons/sequence_check_digit/i18n/ro_RO.po
odoo_addons/sequence_check_digit/i18n/sequence_check_digit.pot
odoo_addons/sequence_check_digit/i18n/sl.po
odoo_addons/sequence_check_digit/models/__init__.py
odoo_addons/sequence_check_digit/models/ir_sequence.py
odoo_addons/sequence_check_digit/static/description/icon.png
odoo_addons/sequence_check_digit/tests/__init__.py
odoo_addons/sequence_check_digit/tests/test_check_digit.py
odoo_addons/sequence_check_digit/views/sequence_views.xml
