Metadata-Version: 2.1
Name: odoo9-addon-sequence-check-digit
Version: 9.0.1.0.0.99.dev4
Summary: Adds a check digit on sequences
Home-page: https://github.com/OCA/server-tools
Author: Creu Blanca, Odoo Community Association (OCA)
Author-email: support@odoo-community.org
License: LGPL-3
Platform: UNKNOWN
Classifier: Programming Language :: Python
Classifier: Framework :: Odoo
Classifier: License :: OSI Approved :: GNU Lesser General Public License v3 (LGPLv3)
Requires-Python: ~=2.7
Requires-Dist: odoo (<9.1a,>=9.0a)
Requires-Dist: python-stdnum
